demo_jupyter_wasm_webgpu_widget/__init__.py
demo_jupyter_wasm_webgpu_widget/widget.py
demo_jupyter_wasm_webgpu_widget/static/aba74fcbff867383830f.wasm
demo_jupyter_wasm_webgpu_widget/static/current_script.js
demo_jupyter_wasm_webgpu_widget/static/widget.js
demo_jupyter_wasm_webgpu_widget-0.1.11.dist-info/METADATA
demo_jupyter_wasm_webgpu_widget-0.1.11.dist-info/WHEEL
demo_jupyter_wasm_webgpu_widget-0.1.11.dist-info/licenses/LICENSE.md
demo_jupyter_wasm_webgpu_widget-0.1.11.dist-info/RECORD
