Metadata-Version: 2.4
Name: demo_jupyter_wasm_webgpu_widget
Version: 0.1.11
Summary: A Custom Jupyter Widget Library
Project-URL: Homepage, https://github.com/Twinklebear/demo_jupyter_wasm_webgpu_widget
Author-email: Will Usher <will@willusher.io>
License: The MIT License (MIT)
License-File: LICENSE.md
Keywords: IPython,Jupyter,Widgets
Requires-Dist: anywidget
